RustPrimer/README.md
RustPrimer/__init__.py
RustPrimer/__main__.py
RustPrimer/file.epub
RustPrimer/index.html
RustPrimer/css/__init__.py
RustPrimer/css/annotations.css
RustPrimer/css/main.css
RustPrimer/css/normalize.css
RustPrimer/css/popup.css
RustPrimer/font/__init__.py
RustPrimer/font/fontello.eot
RustPrimer/font/fontello.svg
RustPrimer/font/fontello.ttf
RustPrimer/font/fontello.woff
RustPrimer/img/__init__.py
RustPrimer/img/annotator-glyph-sprite.png
RustPrimer/img/annotator-icon-sprite.png
RustPrimer/img/apple-touch-icon.png
RustPrimer/img/cancelfullscreen.png
RustPrimer/img/close.png
RustPrimer/img/fullscreen.png
RustPrimer/img/loader.gif
RustPrimer/img/menu-icon.png
RustPrimer/img/save.png
RustPrimer/img/saved.png
RustPrimer/img/settings-s.png
RustPrimer/img/settings.png
RustPrimer/img/star.png
RustPrimer/js/__init__.py
RustPrimer/js/epub.js
RustPrimer/js/epub.min.js
RustPrimer/js/epub.min.map
RustPrimer/js/hooks.min.js
RustPrimer/js/hooks.min.map
RustPrimer/js/reader.js
RustPrimer/js/reader.js.map
RustPrimer/js/reader.min.js
RustPrimer/js/reader.min.map
RustPrimer/js/hooks/__init__.py
RustPrimer/js/hooks/extensions/__init__.py
RustPrimer/js/hooks/extensions/highlight.js
RustPrimer/js/libs/__init__.py
RustPrimer/js/libs/jquery.min.js
RustPrimer/js/libs/localforage.min.js
RustPrimer/js/libs/screenfull.js
RustPrimer/js/libs/screenfull.min.js
RustPrimer/js/libs/zip.min.js
RustPrimer/js/plugins/__init__.py
RustPrimer/js/plugins/hypothesis.js
RustPrimer/js/plugins/search.js
rust_primer-2024.3.2.0.dist-info/METADATA
rust_primer-2024.3.2.0.dist-info/WHEEL
rust_primer-2024.3.2.0.dist-info/entry_points.txt
rust_primer-2024.3.2.0.dist-info/top_level.txt
rust_primer-2024.3.2.0.dist-info/RECORD
